kitconcept.seo-2.1.1-py3.12-nspkg.pth
kitconcept/seo/__init__.py
kitconcept/seo/configure.zcml
kitconcept/seo/dependencies.zcml
kitconcept/seo/interfaces.py
kitconcept/seo/profiles.zcml
kitconcept/seo/subscribers.py
kitconcept/seo/testing.py
kitconcept/seo/behaviors/__init__.py
kitconcept/seo/behaviors/configure.zcml
kitconcept/seo/behaviors/seo.py
kitconcept/seo/locales/__init__.py
kitconcept/seo/locales/kitconcept.seo.pot
kitconcept/seo/locales/update.sh
kitconcept/seo/locales/de/LC_MESSAGES/kitconcept.seo.po
kitconcept/seo/locales/es/LC_MESSAGES/kitconcept.seo.po
kitconcept/seo/locales/it/LC_MESSAGES/kitconcept.seo.po
kitconcept/seo/profiles/default/browserlayer.xml
kitconcept/seo/profiles/default/metadata.xml
kitconcept/seo/profiles/uninstall/browserlayer.xml
kitconcept/seo/setuphandlers/__init__.py
kitconcept/seo/upgrades/__init__.py
kitconcept/seo/upgrades/configure.zcml
kitconcept_seo-2.1.1.dist-info/licenses/LICENSE.GPL
kitconcept_seo-2.1.1.dist-info/licenses/LICENSE.md
kitconcept_seo-2.1.1.dist-info/METADATA
kitconcept_seo-2.1.1.dist-info/WHEEL
kitconcept_seo-2.1.1.dist-info/entry_points.txt
kitconcept_seo-2.1.1.dist-info/namespace_packages.txt
kitconcept_seo-2.1.1.dist-info/top_level.txt
kitconcept_seo-2.1.1.dist-info/RECORD
