Metadata-Version: 2.4
Name: kitconcept.seo
Version: 2.1.1
Summary: SEO optimizations plugin for Plone
Home-page: https://pypi.python.org/pypi/kitconcept.seo
Author: kitconcept GmbH
Author-email: info@kitconcept.com
License: GPL version 2
Project-URL: PyPI, https://pypi.python.org/pypi/kitconcept.seo
Project-URL: Source, https://github.com/kitconcept/kitconcept.seo
Project-URL: Tracker, https://github.com/kitconcept/kitconcept.seo/issues
Keywords: Python Plone CMS
Classifier: Development Status :: 5 - Production/Stable
Classifier: Environment :: Web Environment
Classifier: Framework :: Plone
Classifier: Framework :: Plone :: Addon
Classifier: Framework :: Plone :: 6.0
Classifier: Programming Language :: Python
Classifier: Programming Language :: Python :: 3.8
Classifier: Programming Language :: Python :: 3.9
Classifier: Programming Language :: Python :: 3.10
Classifier: Programming Language :: Python :: 3.11
Classifier: Operating System :: OS Independent
Requires-Python: >=3.8
License-File: LICENSE.GPL
License-File: LICENSE.md
Requires-Dist: setuptools
Requires-Dist: Products.CMFPlone
Requires-Dist: plone.app.dexterity
Requires-Dist: plone.autoform
Requires-Dist: plone.behavior
Requires-Dist: plone.dexterity
Requires-Dist: plone.namedfile
Requires-Dist: plone.supermodel
Provides-Extra: test
Requires-Dist: zest.releaser[recommended]; extra == "test"
Requires-Dist: zestreleaser.towncrier; extra == "test"
Requires-Dist: plone.app.contenttypes[test]; extra == "test"
Requires-Dist: plone.app.testing; extra == "test"
Requires-Dist: plone.restapi[test]; extra == "test"
Requires-Dist: plone.app.iterate; extra == "test"
Requires-Dist: pytest; extra == "test"
Requires-Dist: pytest-cov; extra == "test"
Requires-Dist: pytest-plone>=0.2.0; extra == "test"
Dynamic: author
Dynamic: author-email
Dynamic: classifier
Dynamic: description
Dynamic: description-content-type
Dynamic: home-page
Dynamic: keywords
Dynamic: license
Dynamic: license-file
Dynamic: project-url
Dynamic: provides-extra
Dynamic: requires-dist
Dynamic: requires-python
Dynamic: summary
